ferfereh/__init__.py
ferfereh/__main__.py
ferfereh/coords.py
ferfereh/logger.py
ferfereh/urls.py
ferfereh/utils.py
ferfereh/.abcli/actions.sh
ferfereh/.abcli/exif.sh
ferfereh/.abcli/ferfereh.sh
ferfereh/.abcli/publish.sh
ferfereh/.abcli/tests/version.sh
ferfereh-1.148.1.dist-info/METADATA
ferfereh-1.148.1.dist-info/WHEEL
ferfereh-1.148.1.dist-info/top_level.txt
ferfereh-1.148.1.dist-info/RECORD
