Metadata-Version: 2.1
Name: ferfereh
Version: 1.148.1
Summary: 🌀 3d-printed graffiti.
Home-page: https://github.com/kamangir/ferfereh
Author: Arash Abadpour (Kamangir)
Author-email: arash@kamangir.net
License: Public Domain
Classifier: Programming Language :: Python :: 3
Classifier: Programming Language :: Unix Shell
Classifier: License :: Public Domain
Classifier: Operating System :: OS Independent
Requires-Dist: blueness
Requires-Dist: abcli
Requires-Dist: boto3
Requires-Dist: geojson
Requires-Dist: geopandas
Requires-Dist: matplotlib
Requires-Dist: opencv-python
Requires-Dist: pymysql==0.10.1
Requires-Dist: pyyaml
Requires-Dist: pylint
Requires-Dist: pytest
Requires-Dist: python-dotenv[cli]
Requires-Dist: tqdm
